rlsvision/__init__.py
rlsvision/structures/__init__.py
rlsvision/structures/image.py
rlsvision-0.1.1.dist-info/LICENSE
rlsvision-0.1.1.dist-info/METADATA
rlsvision-0.1.1.dist-info/WHEEL
rlsvision-0.1.1.dist-info/top_level.txt
rlsvision-0.1.1.dist-info/RECORD
