Metadata-Version: 2.1
Name: rlsvision
Version: 0.1.1
Author-email: Mark Mayerfeld <mark.m.mayerfeld@gmail.com>
License: MIT License
Project-URL: repository, https://github.com/RakitaLabSoftware/rlsvision
Requires-Python: >=3.11
License-File: LICENSE
Requires-Dist: torch
Requires-Dist: torchvision
Requires-Dist: opencv-contrib-python
Requires-Dist: lightning
Provides-Extra: dev
Requires-Dist: pytest ; extra == 'dev'
Requires-Dist: black ; extra == 'dev'
Requires-Dist: isort ; extra == 'dev'
Requires-Dist: build ; extra == 'dev'
